[
  {
    "id": "118-1",
    "name": "セブンイレブン武蔵野境2丁目店",
    "image": "https://image.xinu.ink/pic/data/1051/images/118-1.jpg",
    "geo": [
      35.70264,
      139.542184
    ]
  },
  {
    "id": "118-2",
    "name": "らーめん明日があるさ",
    "image": "https://image.xinu.ink/pic/data/1051/images/118-2.jpg",
    "geo": [
      35.705796,
      139.543941
    ]
  },
  {
    "id": "118-3",
    "name": "らーめん明日があるさ",
    "image": "https://image.xinu.ink/pic/data/1051/images/118-3.jpg",
    "geo": [
      35.705728,
      139.544091
    ]
  },
  {
    "id": "118-4",
    "name": "シュガーローゼ、シュガーローゼ隣",
    "image": "https://image.xinu.ink/pic/data/1051/images/118-4.jpg",
    "geo": [
      35.702707,
      139.636359
    ]
  },
  {
    "id": "118-5",
    "name": "シュガーローゼ向かい、シュガーローゼ隣",
    "image": "https://image.xinu.ink/pic/data/1051/images/118-5.jpg",
    "geo": [
      35.702402,
      139.636295
    ]
  },
  {
    "id": "118-6",
    "name": "シュガーローゼ向かい",
    "image": "https://image.xinu.ink/pic/data/1051/images/118-6.jpg",
    "geo": [
      35.702855,
      139.636394
    ]
  },
  {
    "id": "118-7",
    "name": "シュガーローゼ隣",
    "image": "https://image.xinu.ink/pic/data/1051/images/118-7.jpg",
    "geo": [
      35.702742,
      139.636209
    ]
  },
  {
    "id": "118-8",
    "name": "シュガーローゼ隣",
    "image": "https://image.xinu.ink/pic/data/1051/images/118-8.jpg",
    "geo": [
      35.70191,
      139.636002
    ]
  },
  {
    "id": "118-9",
    "name": "シュガーローゼ",
    "image": "https://image.xinu.ink/pic/data/1051/images/118-9.jpg",
    "geo": [
      35.702651,
      139.636188
    ]
  },
  {
    "id": "118-10",
    "name": "シュガーローゼ",
    "image": "https://image.xinu.ink/pic/data/1051/images/118-10.jpg",
    "geo": [
      35.702592,
      139.636346
    ]
  },
  {
    "id": "118-11",
    "name": "荻窪駅北口周辺",
    "image": "https://image.xinu.ink/pic/data/1051/images/118-11.jpg",
    "geo": [
      35.705127,
      139.621264
    ]
  },
  {
    "id": "118-12",
    "name": "荻窪駅北口周辺",
    "image": "https://image.xinu.ink/pic/data/1051/images/118-12.jpg",
    "geo": [
      35.704748,
      139.620786
    ]
  },
  {
    "id": "118-13",
    "name": "ジョナサン下井草店",
    "image": "https://image.xinu.ink/pic/data/1051/images/118-13.jpg",
    "geo": [
      35.719129,
      139.616058
    ]
  },
  {
    "id": "118-14",
    "name": "ジョナサン下井草店",
    "image": "https://image.xinu.ink/pic/data/1051/images/118-14.jpg",
    "geo": [
      35.719118,
      139.615661
    ]
  },
  {
    "id": "118-15",
    "name": "上板橋駅北口周辺",
    "image": "https://image.xinu.ink/pic/data/1051/images/118-15.jpg",
    "geo": [
      35.76358,
      139.677059
    ]
  },
  {
    "id": "118-16",
    "name": "上板橋駅北口周辺",
    "image": "https://image.xinu.ink/pic/data/1051/images/118-16.jpg",
    "geo": [
      35.764004,
      139.677145
    ]
  },
  {
    "id": "118-17",
    "name": "上板橋駅南口周辺",
    "image": "https://image.xinu.ink/pic/data/1051/images/118-17.jpg",
    "geo": [
      35.763371,
      139.676013
    ]
  },
  {
    "id": "118-18",
    "name": "上板橋駅南口周辺",
    "image": "https://image.xinu.ink/pic/data/1051/images/118-18.jpg",
    "geo": [
      35.763294,
      139.675895
    ]
  },
  {
    "id": "118-19",
    "name": "上板橋駅南口周辺",
    "image": "https://image.xinu.ink/pic/data/1051/images/118-19.jpg",
    "geo": [
      35.762946,
      139.675479
    ]
  },
  {
    "id": "118-20",
    "name": "上板橋駅南口周辺",
    "image": "https://image.xinu.ink/pic/data/1051/images/118-20.jpg",
    "geo": [
      35.763035,
      139.675554
    ]
  },
  {
    "id": "118-21",
    "name": "新宿駅地下",
    "image": "https://image.xinu.ink/pic/data/1051/images/118-21.jpg",
    "geo": [
      35.692169,
      139.700121
    ]
  },
  {
    "id": "118-22",
    "name": "高島屋付近（２Ｆ）",
    "image": "https://image.xinu.ink/pic/data/1051/images/118-22.jpg",
    "geo": [
      35.687063,
      139.701985
    ]
  },
  {
    "id": "118-23",
    "name": "新宿駅南口（券売機）",
    "image": "https://image.xinu.ink/pic/data/1051/images/118-23.jpg",
    "geo": [
      35.689457,
      139.700735
    ]
  },
  {
    "id": "118-24",
    "name": "新宿駅南口改札前周辺",
    "image": "https://image.xinu.ink/pic/data/1051/images/118-24.jpg",
    "geo": [
      35.689411,
      139.700453
    ]
  },
  {
    "id": "118-25",
    "name": "新宿駅（５、６番線）",
    "image": "https://image.xinu.ink/pic/data/1051/images/118-25.jpg",
    "geo": [
      35.691117,
      139.700582
    ]
  },
  {
    "id": "118-26",
    "name": "北赤羽駅赤羽口周辺（アクトピア北赤羽壱番館付近）",
    "image": "https://image.xinu.ink/pic/data/1051/images/118-26.jpg",
    "geo": [
      35.786538,
      139.707752
    ]
  },
  {
    "id": "118-27",
    "name": "北赤羽駅赤羽口周辺（アクトピア北赤羽壱番館付近）",
    "image": "https://image.xinu.ink/pic/data/1051/images/118-27.jpg",
    "geo": [
      35.786507,
      139.707824
    ]
  },
  {
    "id": "118-28",
    "name": "北赤羽駅赤羽口周辺（「浮間橋」交差点付近）",
    "image": "https://image.xinu.ink/pic/data/1051/images/118-28.jpg",
    "geo": [
      35.786766,
      139.706673
    ]
  },
  {
    "id": "118-29",
    "name": "興国ゴム赤羽工場周辺",
    "image": "https://image.xinu.ink/pic/data/1051/images/118-29.jpg",
    "geo": [
      35.787332,
      139.708964
    ]
  },
  {
    "id": "118-30",
    "name": "ダイアパレス北赤羽付近",
    "image": "https://image.xinu.ink/pic/data/1051/images/118-30.jpg",
    "geo": [
      35.787963,
      139.708967
    ]
  },
  {
    "id": "118-31",
    "name": "「新河岸川」河川敷北",
    "image": "https://image.xinu.ink/pic/data/1051/images/118-31.jpg",
    "geo": [
      35.788139,
      139.70765
    ]
  },
  {
    "id": "118-32",
    "name": "「新河岸川」河川敷北",
    "image": "https://image.xinu.ink/pic/data/1051/images/118-32.jpg",
    "geo": [
      35.788198,
      139.707835
    ]
  },
  {
    "id": "118-33",
    "name": "浮間橋",
    "image": "https://image.xinu.ink/pic/data/1051/images/118-33.jpg",
    "geo": [
      35.786888,
      139.706357
    ]
  },
  {
    "id": "118-34",
    "name": "「新河岸川」河川敷南",
    "image": "https://image.xinu.ink/pic/data/1051/images/118-34.jpg",
    "geo": [
      35.785835,
      139.705
    ]
  },
  {
    "id": "118-35",
    "name": "「新河岸川」河川敷南",
    "image": "https://image.xinu.ink/pic/data/1051/images/118-35.jpg",
    "geo": [
      35.786303,
      139.705567
    ]
  },
  {
    "id": "118-36",
    "name": "「新河岸川」河川敷南",
    "image": "https://image.xinu.ink/pic/data/1051/images/118-36.jpg",
    "geo": [
      35.786562,
      139.705851
    ]
  },
  {
    "id": "118-37",
    "name": "浮間橋",
    "image": "https://image.xinu.ink/pic/data/1051/images/118-37.jpg",
    "geo": [
      35.787419,
      139.705694
    ]
  },
  {
    "id": "118-38",
    "name": "「新河岸川」河川敷北",
    "image": "https://image.xinu.ink/pic/data/1051/images/118-38.jpg",
    "geo": [
      35.788598,
      139.710892
    ]
  },
  {
    "id": "118-39",
    "name": "北赤羽駅赤羽口周辺（アクトピア北赤羽壱番館付近）",
    "image": "https://image.xinu.ink/pic/data/1051/images/118-39.jpg",
    "geo": [
      35.786494,
      139.707717
    ]
  },
  {
    "id": "118-40",
    "name": "興国ゴム赤羽工場周辺",
    "image": "https://image.xinu.ink/pic/data/1051/images/118-40.jpg",
    "geo": [
      35.787199,
      139.708261
    ]
  },
  {
    "id": "118-41",
    "name": "伊豆急行伊豆急下田駅付近",
    "image": "https://image.xinu.ink/pic/data/1051/images/118-41.jpg",
    "geo": [
      34.678853,
      138.944634
    ]
  },
  {
    "id": "118-42",
    "name": "志賀プリンスホテル",
    "image": "https://image.xinu.ink/pic/data/1051/images/118-42.jpg",
    "geo": [
      36.684845,
      138.497
    ]
  }
]