[
  {
    "id": "302-1",
    "name": "OP　飯能大橋",
    "image": "https://image.xinu.ink/pic/data/1215/images/302-1.jpg",
    "geo": [
      35.848594,
      139.316152
    ]
  },
  {
    "id": "302-2",
    "name": "第01話　飯能大橋",
    "image": "https://image.xinu.ink/pic/data/1215/images/302-2.jpg",
    "geo": [
      35.848526,
      139.31609
    ]
  },
  {
    "id": "302-3",
    "name": "第01話　コジマ木材付近",
    "image": "https://image.xinu.ink/pic/data/1215/images/302-3.jpg",
    "geo": [
      35.848759,
      139.313502
    ]
  },
  {
    "id": "302-4",
    "name": "第01話　滝沢神社付近",
    "image": "https://image.xinu.ink/pic/data/1215/images/302-4.jpg",
    "geo": [
      35.848985,
      139.312839
    ]
  },
  {
    "id": "302-5",
    "name": "第01話　大鵬薬品付近",
    "image": "https://image.xinu.ink/pic/data/1215/images/302-5.jpg",
    "geo": [
      35.847096,
      139.310246
    ]
  },
  {
    "id": "302-6",
    "name": "第06話　飯能大橋",
    "image": "https://image.xinu.ink/pic/data/1215/images/302-6.jpg",
    "geo": [
      35.848141,
      139.315698
    ]
  },
  {
    "id": "302-7",
    "name": "第06話　飯能大橋",
    "image": "https://image.xinu.ink/pic/data/1215/images/302-7.jpg",
    "geo": [
      35.8482,
      139.31561
    ]
  },
  {
    "id": "302-8",
    "name": "第12話　飯能駅改札口",
    "image": "https://image.xinu.ink/pic/data/1215/images/302-8.jpg",
    "geo": [
      35.850983,
      139.319204
    ]
  }
]