[
  {
    "id": "396-0",
    "name": "海浜幕張駅南口",
    "image": "https://image.xinu.ink/pic/data/1305/images/396-0.jpg",
    "geo": [
      35.6481065,
      140.0416746
    ]
  },
  {
    "id": "396-1",
    "name": "海浜幕張駅南口にある交差点",
    "image": "https://image.xinu.ink/pic/data/1305/images/396-1.jpg",
    "geo": [
      35.6487713,
      140.0408404
    ]
  },
  {
    "id": "396-2",
    "name": "海浜幕張駅北口ペデストリアンデッキ",
    "image": "https://image.xinu.ink/pic/data/1305/images/396-2.jpg",
    "geo": [
      35.6493172,
      140.0413595
    ]
  },
  {
    "id": "396-3",
    "name": "海浜幕張駅北口",
    "image": "https://image.xinu.ink/pic/data/1305/images/396-3.jpg",
    "geo": [
      35.6489467,
      140.0417697
    ]
  },
  {
    "id": "396-4",
    "name": "「海浜幕張駅北口」交差点",
    "image": "https://image.xinu.ink/pic/data/1305/images/396-4.jpg",
    "geo": [
      35.6498055,
      140.0414023
    ]
  },
  {
    "id": "396-5",
    "name": "多摩桜ヶ丘郵便局付近",
    "image": "https://image.xinu.ink/pic/data/1305/images/396-5.jpg",
    "geo": [
      35.6411239,
      139.4448012
    ]
  },
  {
    "id": "396-6",
    "name": "いろは坂桜公園",
    "image": "https://image.xinu.ink/pic/data/1305/images/396-6.jpg",
    "geo": [
      35.645479,
      139.4451284
    ]
  },
  {
    "id": "396-7",
    "name": "大栗川沿い",
    "image": "https://image.xinu.ink/pic/data/1305/images/396-7.jpg",
    "geo": [
      35.6475366,
      139.4481272
    ]
  },
  {
    "id": "396-8",
    "name": "いろは坂",
    "image": "https://image.xinu.ink/pic/data/1305/images/396-8.jpg",
    "geo": [
      35.6453656,
      139.4447047
    ]
  },
  {
    "id": "396-9",
    "name": "多摩市桜ヶ丘２丁目Ａ",
    "image": "https://image.xinu.ink/pic/data/1305/images/396-9.jpg",
    "geo": [
      35.6375511,
      139.439477
    ]
  },
  {
    "id": "396-10",
    "name": "多摩市桜ヶ丘２丁目Ｂ",
    "image": "https://image.xinu.ink/pic/data/1305/images/396-10.jpg",
    "geo": [
      35.6374748,
      139.43941
    ]
  },
  {
    "id": "396-12",
    "name": "多摩市桜ヶ丘２丁目Ｄ",
    "image": "https://image.xinu.ink/pic/data/1305/images/396-12.jpg",
    "geo": [
      35.6377844,
      139.4397962
    ]
  },
  {
    "id": "396-14",
    "name": "いろは坂",
    "image": "https://image.xinu.ink/pic/data/1305/images/396-14.jpg",
    "geo": [
      35.6457078,
      139.4451419
    ]
  },
  {
    "id": "396-16",
    "name": "ＪＲ東日本上野総合事務所前にある交差点",
    "image": "https://image.xinu.ink/pic/data/1305/images/396-16.jpg",
    "geo": [
      35.7174365,
      139.7806191
    ]
  },
  {
    "id": "396-17",
    "name": "上野駅不忍口前にある交差点",
    "image": "https://image.xinu.ink/pic/data/1305/images/396-17.jpg",
    "geo": [
      35.7114389,
      139.7745547
    ]
  },
  {
    "id": "396-18",
    "name": "上野駅不忍口前にある交差点",
    "image": "https://image.xinu.ink/pic/data/1305/images/396-18.jpg",
    "geo": [
      35.7118897,
      139.7747424
    ]
  },
  {
    "id": "396-19",
    "name": "上野駅ペデストリアンデッキ",
    "image": "https://image.xinu.ink/pic/data/1305/images/396-19.jpg",
    "geo": [
      35.7112081,
      139.7766173
    ]
  },
  {
    "id": "396-20",
    "name": "B-COMPANY Transit 吉祥寺・中道通り店",
    "image": "https://image.xinu.ink/pic/data/1305/images/396-20.jpg",
    "geo": [
      35.7036962,
      139.5768356
    ]
  },
  {
    "id": "396-21",
    "name": "旧ブックスいずみ（エクセルシオールカフェ 吉祥寺サンロード店）",
    "image": "https://image.xinu.ink/pic/data/1305/images/396-21.jpg",
    "geo": [
      35.7026508,
      139.5793918
    ]
  },
  {
    "id": "396-22",
    "name": "吉祥寺パルコ付近",
    "image": "https://image.xinu.ink/pic/data/1305/images/396-22.jpg",
    "geo": [
      35.7033565,
      139.57771
    ]
  },
  {
    "id": "396-23",
    "name": "TLIPルミネエスト新宿店",
    "image": "https://image.xinu.ink/pic/data/1305/images/396-23.jpg",
    "geo": [
      35.6914458,
      139.7010246
    ]
  },
  {
    "id": "396-25",
    "name": "茶乃子",
    "image": "https://image.xinu.ink/pic/data/1305/images/396-25.jpg",
    "geo": [
      35.6067653,
      139.6693665
    ]
  },
  {
    "id": "396-26",
    "name": "MONCEAU FLEURS （モンソーフルール） 自由が丘本店とSHUTTERS 自由が丘",
    "image": "https://image.xinu.ink/pic/data/1305/images/396-26.jpg",
    "geo": [
      35.6065734,
      139.6686181
    ]
  },
  {
    "id": "396-27",
    "name": "Caffe Bus muraccho （カフェバス ムラッチョ）",
    "image": "https://image.xinu.ink/pic/data/1305/images/396-27.jpg",
    "geo": [
      35.6065908,
      139.6689668
    ]
  },
  {
    "id": "396-28",
    "name": "自由が丘MAST",
    "image": "https://image.xinu.ink/pic/data/1305/images/396-28.jpg",
    "geo": [
      35.6069114,
      139.669683
    ]
  },
  {
    "id": "396-30",
    "name": "海浜幕張駅南口（タクシー乗り場）",
    "image": "https://image.xinu.ink/pic/data/1305/images/396-30.jpg",
    "geo": [
      35.6481904,
      140.0411421
    ]
  },
  {
    "id": "396-31",
    "name": "幕張テクノガーデン付近",
    "image": "https://image.xinu.ink/pic/data/1305/images/396-31.jpg",
    "geo": [
      35.6503133,
      140.0420165
    ]
  },
  {
    "id": "396-32",
    "name": "幕張テクノガーデン付近",
    "image": "https://image.xinu.ink/pic/data/1305/images/396-32.jpg",
    "geo": [
      35.6504833,
      140.0423652
    ]
  },
  {
    "id": "396-33",
    "name": "「海浜幕張駅北口」交差点（北）",
    "image": "https://image.xinu.ink/pic/data/1305/images/396-33.jpg",
    "geo": [
      35.6499275,
      140.0415391
    ]
  },
  {
    "id": "396-34",
    "name": "海浜幕張駅北口ペデストリアンデッキ",
    "image": "https://image.xinu.ink/pic/data/1305/images/396-34.jpg",
    "geo": [
      35.6495287,
      140.0411448
    ]
  },
  {
    "id": "396-35",
    "name": "幕張テクノガーデン付近",
    "image": "https://image.xinu.ink/pic/data/1305/images/396-35.jpg",
    "geo": [
      35.6501172,
      140.041185
    ]
  },
  {
    "id": "396-36",
    "name": "「海浜幕張駅北口」交差点（西）",
    "image": "https://image.xinu.ink/pic/data/1305/images/396-36.jpg",
    "geo": [
      35.6496377,
      140.0411958
    ]
  },
  {
    "id": "396-37",
    "name": "「東寺方三丁目」バス停付近の交差点",
    "image": "https://image.xinu.ink/pic/data/1305/images/396-37.jpg",
    "geo": [
      35.637392,
      139.438836
    ]
  },
  {
    "id": "396-38",
    "name": "若洲海浜公園",
    "image": "https://image.xinu.ink/pic/data/1305/images/396-38.jpg",
    "geo": [
      35.6141859,
      139.8347408
    ]
  },
  {
    "id": "396-40",
    "name": "臨港パーク",
    "image": "https://image.xinu.ink/pic/data/1305/images/396-40.jpg",
    "geo": [
      35.4620769,
      139.6374965
    ]
  },
  {
    "id": "396-41",
    "name": "上野恩賜公園",
    "image": "https://image.xinu.ink/pic/data/1305/images/396-41.jpg",
    "geo": [
      35.7165959,
      139.7746432
    ]
  },
  {
    "id": "396-42",
    "name": "海浜幕張駅南口",
    "image": "https://image.xinu.ink/pic/data/1305/images/396-42.jpg",
    "geo": [
      35.6479485,
      140.0412387
    ]
  },
  {
    "id": "396-43",
    "name": "海浜幕張駅北口ペデストリアンデッキ",
    "image": "https://image.xinu.ink/pic/data/1305/images/396-43.jpg",
    "geo": [
      35.6493282,
      140.0412521
    ]
  },
  {
    "id": "396-44",
    "name": "遊行寺",
    "image": "https://image.xinu.ink/pic/data/1305/images/396-44.jpg",
    "geo": [
      35.3482173,
      139.4884998
    ]
  }
]