[
  {
    "id": "284-1",
    "name": "高徳院 鎌倉大仏",
    "image": "https://image.xinu.ink/pic/data/1199/images/284-1.jpg",
    "geo": [
      35.316845,
      139.535728
    ]
  },
  {
    "id": "284-2",
    "name": "高徳院 仁王門",
    "image": "https://image.xinu.ink/pic/data/1199/images/284-2.jpg",
    "geo": [
      35.3159,
      139.535393
    ]
  },
  {
    "id": "284-3",
    "name": "鶴岡八幡宮",
    "image": "https://image.xinu.ink/pic/data/1199/images/284-3.jpg",
    "geo": [
      35.325934,
      139.556327
    ]
  },
  {
    "id": "284-4",
    "name": "六本木交差点",
    "image": "https://image.xinu.ink/pic/data/1199/images/284-4.jpg",
    "geo": [
      35.663237,
      139.732221
    ]
  },
  {
    "id": "284-5",
    "name": "妙喜禅庵 待庵",
    "image": "https://image.xinu.ink/pic/data/1199/images/284-5.jpg",
    "geo": [
      34.892184,
      135.680342
    ]
  },
  {
    "id": "284-7",
    "name": "北野天満宮",
    "image": "https://image.xinu.ink/pic/data/1199/images/284-7.jpg",
    "geo": [
      35.031224,
      135.735097
    ]
  },
  {
    "id": "284-8",
    "name": "大徳寺",
    "image": "https://image.xinu.ink/pic/data/1199/images/284-8.jpg",
    "geo": [
      35.042655,
      135.746153
    ]
  },
  {
    "id": "284-9",
    "name": "妙覚寺",
    "image": "https://image.xinu.ink/pic/data/1199/images/284-9.jpg",
    "geo": [
      35.036895,
      135.754007
    ]
  }
]